pypaya_python_tools/__init__.py
pypaya_python_tools/code_manipulation/__init__.py
pypaya_python_tools/code_manipulation/logging.py
pypaya_python_tools/coding_with_llms/__init__.py
pypaya_python_tools/coding_with_llms/file_structure.py
pypaya_python_tools/decorating/__init__.py
pypaya_python_tools/decorating/behavior.py
pypaya_python_tools/decorating/debug.py
pypaya_python_tools/decorating/error_handling.py
pypaya_python_tools/decorating/performance.py
pypaya_python_tools/execution/__init__.py
pypaya_python_tools/execution/repl.py
pypaya_python_tools/imports/__init__.py
pypaya_python_tools/imports/dynamic_importer.py
pypaya_python_tools/object_generation/__init__.py
pypaya_python_tools/object_generation/object_generator.py
pypaya_python_tools/package_management/__init__.py
pypaya_python_tools/package_management/base.py
pypaya_python_tools/package_management/conda_manager.py
pypaya_python_tools/package_management/exceptions.py
pypaya_python_tools/package_management/factory.py
pypaya_python_tools/package_management/pip_manager.py
pypaya_python_tools/package_management/utils.py
pypaya_python_tools-1.2.0.dist-info/LICENSE
pypaya_python_tools-1.2.0.dist-info/METADATA
pypaya_python_tools-1.2.0.dist-info/WHEEL
pypaya_python_tools-1.2.0.dist-info/top_level.txt
pypaya_python_tools-1.2.0.dist-info/RECORD
