Metadata-Version: 2.1
Name: pypaya-python-tools
Version: 1.2.0
Summary: Awesome Python code for Python developers to make working with Python easier.
Author: PypayaTech
License: MIT
Project-URL: Homepage, https://github.com/PypayaTech/pypaya-python-tools
Project-URL: Repository, https://github.com/PypayaTech/pypaya-python-tools.git
Keywords: development,tools,utilities,productivity,ai
Classifier: Development Status :: 3 - Alpha
Classifier: Intended Audience :: Developers
Classifier: License :: OSI Approved :: MIT License
Classifier: Operating System :: OS Independent
Classifier: Programming Language :: Python :: 3
Classifier: Programming Language :: Python :: 3.7
Classifier: Programming Language :: Python :: 3.8
Classifier: Programming Language :: Python :: 3.9
Classifier: Programming Language :: Python :: 3.10
Classifier: Programming Language :: Python :: 3.11
Requires-Python: >=3.7
License-File: LICENSE
Requires-Dist: astor
Provides-Extra: test
Requires-Dist: pytest>=6.0; extra == "test"
Requires-Dist: pytest-cov>=2.0; extra == "test"
